snowshu/__init__.py
snowshu/configs.py
snowshu/exceptions.py
snowshu/formats.py
snowshu/logger.py
snowshu/adapters/__init__.py
snowshu/adapters/base_sql_adapter.py
snowshu/adapters/source_adapters/__init__.py
snowshu/adapters/source_adapters/base_source_adapter.py
snowshu/adapters/source_adapters/snowflake_adapter.py
snowshu/adapters/target_adapters/__init__.py
snowshu/adapters/target_adapters/base_target_adapter.py
snowshu/adapters/target_adapters/postgres_adapter/__init__.py
snowshu/adapters/target_adapters/postgres_adapter/postgres_adapter.py
snowshu/adapters/target_adapters/postgres_adapter/functions/ANY_VALUE.sql
snowshu/adapters/target_adapters/postgres_adapter/functions/RLIKE.sql
snowshu/adapters/target_adapters/postgres_adapter/functions/UUID_STRING.sql
snowshu/adapters/target_adapters/postgres_adapter/functions/__init__.py
snowshu/core/__init__.py
snowshu/core/compile.py
snowshu/core/configuration_parser.py
snowshu/core/docker.py
snowshu/core/graph.py
snowshu/core/graph_set_runner.py
snowshu/core/main.py
snowshu/core/printable_result.py
snowshu/core/utils.py
snowshu/core/models/__init__.py
snowshu/core/models/attribute.py
snowshu/core/models/credentials.py
snowshu/core/models/data_types.py
snowshu/core/models/materializations.py
snowshu/core/models/relation.py
snowshu/core/replica/__init__.py
snowshu/core/replica/replica_factory.py
snowshu/core/replica/replica_manager.py
snowshu/core/samplings/__init__.py
snowshu/core/samplings/utils.py
snowshu/core/samplings/bases/__init__.py
snowshu/core/samplings/bases/base_sample_method.py
snowshu/core/samplings/bases/base_sample_size.py
snowshu/core/samplings/bases/base_sampling.py
snowshu/samplings/__init__.py
snowshu/samplings/sample_methods/__init__.py
snowshu/samplings/sample_methods/bernoulli_sample_method.py
snowshu/samplings/sample_sizes/__init__.py
snowshu/samplings/sample_sizes/brute_force_sample_size.py
snowshu/samplings/sample_sizes/cochrans_sample_size.py
snowshu/samplings/samplings/__init__.py
snowshu-0.0.4a1.dist-info/LICENSE.md
snowshu-0.0.4a1.dist-info/METADATA
snowshu-0.0.4a1.dist-info/WHEEL
snowshu-0.0.4a1.dist-info/entry_points.txt
snowshu-0.0.4a1.dist-info/top_level.txt
snowshu-0.0.4a1.dist-info/RECORD
